tess_backdrop/__init__.py
tess_backdrop/backdrop.py
tess_backdrop/tesscutcorrector.py
tess_backdrop/version.py
tess_backdrop-0.1.6.dist-info/LICENSE
tess_backdrop-0.1.6.dist-info/WHEEL
tess_backdrop-0.1.6.dist-info/METADATA
tess_backdrop-0.1.6.dist-info/RECORD
