Metadata-Version: 2.1
Name: tess-backdrop
Version: 0.1.6
Summary: 
Author: Christina Hedges
Author-email: christina.l.hedges@nasa.gov
Requires-Python: >=3.8,<3.10
Classifier: Programming Language :: Python :: 3
Classifier: Programming Language :: Python :: 3.8
Classifier: Programming Language :: Python :: 3.9
Requires-Dist: astropy (>=4.2.1,<5.0.0)
Requires-Dist: fbpca (>=1.0,<2.0)
Requires-Dist: fitsio (>=1.1.4,<2.0.0)
Requires-Dist: lightkurve (>=2.0.9,<3.0.0)
Requires-Dist: matplotlib (>=3.4.1,<4.0.0)
Requires-Dist: mkdocs (>=1.1.2,<2.0.0)
Requires-Dist: mkdocs-jupyter (>=0.17.3,<0.18.0)
Requires-Dist: mkdocs-material (>=7.1.3,<8.0.0)
Requires-Dist: mkdocstrings (>=0.15.0,<0.16.0)
Requires-Dist: scipy (>=1.6.3,<2.0.0)
